verilog/adc_control/define.vh
module globals ();

   //Dimensions of the cap-matrix
   parameter MATRIX_ROWS = 16;
   parameter MATRIX_COLS = 32;
   parameter MATRIX_BINS = 3;
   parameter MATRIX_BITS = 12;


   parameter NONBINARY_LUT_WIDTH = 14;

   parameter OSR_BITS = 4;
   parameter RESULT_BITS     = MATRIX_BITS;
   parameter RESULT_OSR_BITS = MATRIX_BITS + OSR_BITS;

endmodule

verilog/adc_control_nonbinary.v
`default_nettype none
//`include "define.vh"

//  Copyright 2022 Manuel Moser
//
//   Licensed under the Apache License, Version 2.0 (the "License");
//   you may not use this file except in compliance with the License.
//   You may obtain a copy of the License at
//
//       http://www.apache.org/licenses/LICENSE-2.0
//
//   Unless required by applicable law or agreed to in writing, software
//   distributed under the License is distributed on an "AS IS" BASIS,
//   WITHOUT WARRANTIES OR CONDITIONS OF ANY KIND, either express or implied.
//   See the License for the specific language governing permissions and
//   limitations under the License.


//Top module ADC Control
module adc_control_nonbinary #(parameter MATRIX_BITS = 12, NONBINARY_REDUNDANCY = 3)(
   input wire clk,
   input wire rst,
   input wire comparator_in,
   input wire [2:0] avg_control,
   output wire sample,
   output wire nsample,
   output reg enable,
   output wire conv_finished,
   output reg[MATRIX_BITS-1:0]  p_switch,
   output reg[MATRIX_BITS-1:0]  n_switch,
   output reg[MATRIX_BITS-1:0]  result
   );

   // internal wires and registers
   reg  next_enable;
   reg  [MATRIX_BITS-1:0] next_result;

   reg averaging;
   reg [4:0] average_counter;
   reg [4:0] next_average_counter;
   reg [4:0] average_count_limit;
   reg [5:0] average_sum;
   reg [5:0] next_average_sum;
   reg average_result;
   reg lsb_region;
   reg [2:0] sampled_avg_control;
   reg [2:0] next_sampled_avg_control;
   
   reg [MATRIX_BITS+NONBINARY_REDUNDANCY:0] shift_register;
   reg [MATRIX_BITS+NONBINARY_REDUNDANCY:0] next_shift_register;
   reg [MATRIX_BITS-1:0] data_register;
   reg [MATRIX_BITS-1:0] next_data_register;
   reg [MATRIX_BITS-1:0] nonbinary_value;
   reg [MATRIX_BITS-1:0] data_add;
   reg [MATRIX_BITS-1:0] data_sub;


   // asynchron signals
   assign sample = shift_register[0];
   assign nsample = ~shift_register[0];
   assign conv_finished = shift_register[0];



   //asynchronous enable signal
   //assign enable = rst & shift_register(0);

   // Clock and Reset Handling
   always @(posedge clk, negedge rst) begin
      if (rst == 1'b0) begin  
         enable <= 1'b0;
         result    <= {MATRIX_BITS{1'b0}};
      end 
      else begin	
         enable         <= next_enable;
         result         <= next_result;
      end
   end //always @clk, rst

    //*******************************
    //   Enable Handling
    //*******************************
    always @(averaging,shift_register) begin
       next_enable <= ~(shift_register[1] && ~averaging);
    end
    //*******************************
    //   Shift Register Handling
    //*******************************
   always @(posedge clk, negedge rst) begin
      if (rst == 1'b0)  //reset ACTIVE LOW
         shift_register <= {{(MATRIX_BITS+NONBINARY_REDUNDANCY){1'b0}},1'b1};     
      else   
         shift_register <= next_shift_register; 
   end //always clk, rst

   always @(averaging,shift_register) begin
      if (averaging)
        next_shift_register <= shift_register;
      else   
        next_shift_register <= {shift_register[0],shift_register[MATRIX_BITS+NONBINARY_REDUNDANCY:1]}; //SRR
   end //always

    //*******************************
    //   Control signals handling
    //*******************************
   always @(posedge clk, negedge rst) begin
      if (rst == 1'b0)  //reset ACTIVE LOW
         sampled_avg_control <= 3'b000;     
      else 
         sampled_avg_control <= next_sampled_avg_control; 
   end //always clk, rst
   
   always @(shift_register,sampled_avg_control,avg_control) begin
   if (shift_register[0]==1'b1)
       next_sampled_avg_control <= avg_control;
   else
       next_sampled_avg_control <= sampled_avg_control;
   end //always


    //*******************************
    //   Data Register Handling
    //   Result handling
    //*******************************
   always @(posedge clk, negedge rst) begin
      if (rst == 1'b0)  //reset ACTIVE LOW
         data_register <= {MATRIX_BITS{1'b0}};   
      else   
         data_register <= next_data_register;
   end //always clk, rst

   always @(averaging,data_register,shift_register,nonbinary_value,result,next_data_register,average_result) begin
      n_switch <= data_register + nonbinary_value;
      p_switch <= ~(data_register + nonbinary_value);
      if (averaging) begin
        next_data_register <= data_register;
        next_result <= result;
      end else begin   
        if (shift_register[0]==1'b1) begin
           next_data_register <= {MATRIX_BITS{1'b0}};
        end else if (average_result) begin
           next_data_register <= data_register + nonbinary_value;
        end else begin
           next_data_register <= data_register;
        end

        if (shift_register[1]==1'b1) 
           next_result <= next_data_register;
        else
           next_result <= result;
      end  
   end //always

    //*******************************
    //      NONBINARY VALUES
    //*******************************
   //Lookuptable for Nonbinary Value
   // 12 Bit Matrix + 3 redundant Bits
   always @(shift_register) begin
      casex (shift_register)
         16'd2**0:  nonbinary_value <= 12'd0; 
         16'd2**15: nonbinary_value <= 12'd1792; 
         16'd2**14: nonbinary_value <= 12'd1024; 
         16'd2**13: nonbinary_value <= 12'd512; 
         16'd2**12: nonbinary_value <= 12'd320; 
         16'd2**11: nonbinary_value <= 12'd192; 
         16'd2**10: nonbinary_value <= 12'd96; 
         16'd2**9:  nonbinary_value <= 12'd64; 
         16'd2**8:  nonbinary_value <= 12'd32; 
         16'd2**7:  nonbinary_value <= 12'd24; 
         16'd2**6:  nonbinary_value <= 12'd16; 
         16'd2**5:  nonbinary_value <= 12'd10; 
         16'd2**4:  nonbinary_value <= 12'd6; 
         16'd2**3:  nonbinary_value <= 12'd4; 
         16'd2**2:  nonbinary_value <= 12'd2; 
         16'd2**1:  nonbinary_value <= 12'd1; 
         default:   nonbinary_value <= 12'dx;
      endcase
    end //always

    //*******************************
    //       AVERAGING
    //*******************************
   // Clock and Reset Handling
   always @(posedge clk, negedge rst) begin
      if (rst == 1'b0) begin                    //reset ACTIVE LOW
        average_counter <= 5'd1;
        average_sum     <= 5'd0;
      end 
      else begin  
        average_counter <= next_average_counter;
        average_sum     <= next_average_sum;
      end
   end //always @clk, rst    


   // Determine if averaging conditions are met
   always @(shift_register) begin
      lsb_region = (shift_register[1] | shift_register[2] | shift_register[3] | shift_register[4]);
   end
   
   always @(average_counter,average_count_limit,lsb_region) begin
         //average lower 3 bits
      if (lsb_region && (average_counter < average_count_limit))
         averaging  <= 1'd1;
      else
         averaging  <= 1'd0;
   end //always

   always @(average_counter,next_average_sum,sampled_avg_control,comparator_in,average_sum,averaging,average_result) begin
      //average lower 3 bits
      if (averaging) begin
         next_average_counter <= average_counter+1;
         next_average_sum     <= average_sum+comparator_in;
         average_result  <= average_result;
      end else if (lsb_region) begin
         next_average_counter <= 5'd1;
         next_average_sum     <= {4'b0000, comparator_in};
         case (sampled_avg_control)
            3'b001:  average_result <= average_sum[1];
            3'b010:  average_result <= average_sum[2];
            3'b011:  average_result <= average_sum[3];
            3'b100:  average_result <= average_sum[4];
            default: average_result <= comparator_in;
         endcase
      end else begin
         next_average_counter <= 5'd1;
         next_average_sum     <= {4'b0000, comparator_in};
         average_result <= comparator_in;
      end
    end

    //Lookuptable for Averaging Limit
    always @(sampled_avg_control) begin
      case (sampled_avg_control)
         3'b001:  average_count_limit <= 5'd3; 
         3'b010:  average_count_limit <= 5'd7; 
         3'b011:  average_count_limit <= 5'd15; 
         3'b100:  average_count_limit <= 5'd31;
         default: average_count_limit <= 5'd1; 
      endcase
    end 
    
endmodule

verilog/adc_top/adc_control_nonbinary_tb.v
//  Copyright 2022 Manuel Moser
//
//   Licensed under the Apache License, Version 2.0 (the "License");
//   you may not use this file except in compliance with the License.
//   You may obtain a copy of the License at
//
//       http://www.apache.org/licenses/LICENSE-2.0
//
//   Unless required by applicable law or agreed to in writing, software
//   distributed under the License is distributed on an "AS IS" BASIS,
//   WITHOUT WARRANTIES OR CONDITIONS OF ANY KIND, either express or implied.
//   See the License for the specific language governing permissions and
//   limitations under the License.

`include "adc_control_nonbinary.v"
`timescale 10us/1us

module adc_control_nonbinary_tb;
  parameter MATRIX_BITS = 12;
  reg clk;
  reg rst;
  reg comparator_in;
  reg [2:0] avg_control;
  wire sample;
  wire nsample;
  wire enable;
  wire conv_finished;
  wire[MATRIX_BITS-1:0]  p_switch;
  wire[MATRIX_BITS-1:0]  n_switch;
  wire[MATRIX_BITS-1:0]  result;

  adc_control_nonbinary testmodule (
	   .clk(clk),
	   .rst(rst),
	   .comparator_in(comparator_in),
	   .avg_control(avg_control),
	   .sample(sample),
	   .nsample(nsample),
	   .enable(enable),
	   .conv_finished(conv_finished),
	   .p_switch(p_switch),
	   .n_switch(n_switch),
	   .result(result)
	   );	

   initial begin
   	$dumpfile("dump.vcd");
   	$dumpvars(0,
   		clk,
   		rst,
   		comparator_in,
   		avg_control,
   		sample,
   		nsample,
   		enable,
   		conv_finished,
   		p_switch,
   		n_switch,
   		result,
   		testmodule);
   end
   
   initial begin
   	#1 rst=1;
    #1 rst=0;
    #1 rst=1;
    #1 rst=1; avg_control = 3'b001;
    #1 comparator_in = 0;

    // first value is d1792
    avg_control = 3'b001; //4x averaging    
    #2 comparator_in = 0; //0001
    #2 comparator_in = 1; //8000
    #2 comparator_in = 0; //4000
    #2 comparator_in = 0; //2000
    #2 comparator_in = 0; //1000
    #2 comparator_in = 0; //0800
    #2 comparator_in = 0; //0400
    #2 comparator_in = 0; //0200
    #2 comparator_in = 0; //0100
    #2 comparator_in = 0; //0080
    #2 comparator_in = 0; //0040
    #2 comparator_in = 0; //0020
    //averaging
    #2 comparator_in = 0; //0010
    #2 comparator_in = 0;
    #2 comparator_in = 0;
    //averaging
    #2 comparator_in = 0; //0008
    #2 comparator_in = 0;
    #2 comparator_in = 0;
    //averaging
    #2 comparator_in = 0; //0004
    #2 comparator_in = 0;
    #2 comparator_in = 0;
    //averaging
    #2 comparator_in = 0; //0002
    #2 comparator_in = 0;
    #2 comparator_in = 0;
        

    // second value is d1024
    avg_control = 3'b000; //0x averaging
    #2 comparator_in = 0; //0001
    #2 comparator_in = 0; //8000
    #2 comparator_in = 1; //4000
    #2 comparator_in = 0; //2000
    #2 comparator_in = 0; //1000
    #2 comparator_in = 0; //0800
    #2 comparator_in = 0; //0400
    #2 comparator_in = 0; //0200
    #2 comparator_in = 0; //0100
    #2 comparator_in = 0; //0080
    #2 comparator_in = 0; //0040
    #2 comparator_in = 0; //0020
    //averaging
    #2 comparator_in = 0; //0010
    //averaging
    #2 comparator_in = 0; //0008
    //averaging
    #2 comparator_in = 0; //0004
    //averaging
    #2 comparator_in = 0; //0002
    
    // third value is d13
    avg_control = 3'b000; //0x averaging
    #2 comparator_in = 0; //0001
    #2 comparator_in = 0; //8000
    #2 comparator_in = 0; //4000
    #2 comparator_in = 0; //2000
    #2 comparator_in = 0; //1000
    #2 comparator_in = 0; //0800
    #2 comparator_in = 0; //0400
    #2 comparator_in = 0; //0200
    #2 comparator_in = 0; //0100
    #2 comparator_in = 0; //0080
    #2 comparator_in = 0; //0040
    #2 comparator_in = 0; //0020
    //averaging
    #2 comparator_in = 1; //0010
    //averaging
    #2 comparator_in = 1; //0008
    //averaging
    #2 comparator_in = 1; //0004
    //averaging
    #2 comparator_in = 1; //0002

    // fourth value is d515
    avg_control = 3'b010; //8x averaging
    #2 comparator_in = 0; //0001
    #2 comparator_in = 0; //8000
    #2 comparator_in = 0; //4000
    #2 comparator_in = 1; //2000 +512
    #2 comparator_in = 0; //1000
    #2 comparator_in = 0; //0800
    #2 comparator_in = 0; //0400
    #2 comparator_in = 0; //0200
    #2 comparator_in = 0; //0100
    #2 comparator_in = 0; //0080
    #2 comparator_in = 0; //0040
    #2 comparator_in = 0; //0020
    //averaging
    #2 comparator_in = 0; //0010
    #2 comparator_in = 1; 
    #2 comparator_in = 0; 
    #2 comparator_in = 1; 
    #2 comparator_in = 0; 
    #2 comparator_in = 0; 
    #2 comparator_in = 0; 
    //averaging
    #2 comparator_in = 0; //0008
    #2 comparator_in = 0; 
    #2 comparator_in = 0;
    #2 comparator_in = 0; 
    #2 comparator_in = 0; 
    #2 comparator_in = 0; 
    #2 comparator_in = 1; 
    //averaging
    #2 comparator_in = 1; //0010 +2
    #2 comparator_in = 0; 
    #2 comparator_in = 0;
    #2 comparator_in = 1; 
    #2 comparator_in = 0; 
    #2 comparator_in = 1; 
    #2 comparator_in = 1; 
    //averaging
    #2 comparator_in = 1; //0010 +1
    #2 comparator_in = 1; 
    #2 comparator_in = 1; 
    #2 comparator_in = 1; 
    #2 comparator_in = 1; 
    #2 comparator_in = 1; 
    #2 comparator_in = 1; 
    

    // fifth value is max value with max averaging d4095
    avg_control = 3'b100; //0x averaging
    #2 comparator_in = 0; //0001
    #2 comparator_in = 1; //8000
    #2 comparator_in = 1; //4000
    #2 comparator_in = 1; //2000
    #2 comparator_in = 1; //1000
    #2 comparator_in = 1; //0800
    #2 comparator_in = 1; //0400
    #2 comparator_in = 1; //0200
    #2 comparator_in = 1; //0100
    #2 comparator_in = 1; //0080
    #2 comparator_in = 1; //0040
    #2 comparator_in = 1; //0020
    //averaging
    #2 comparator_in = 1; //0010
    #2 comparator_in = 1; 
    #2 comparator_in = 1; 
    #2 comparator_in = 1; 
    #2 comparator_in = 1; 
    #2 comparator_in = 1; 
    #2 comparator_in = 1; 
    #2 comparator_in = 1; 
    #2 comparator_in = 1; 
    #2 comparator_in = 1; 
    #2 comparator_in = 1; 
    #2 comparator_in = 1; 
    #2 comparator_in = 1; 
    #2 comparator_in = 1; 
    #2 comparator_in = 1; 
    #2 comparator_in = 1; 
    #2 comparator_in = 1; 
    #2 comparator_in = 1; 
    #2 comparator_in = 1; 
    #2 comparator_in = 1; 
    #2 comparator_in = 1; 
    #2 comparator_in = 1; 
    #2 comparator_in = 1; 
    #2 comparator_in = 1; 
    #2 comparator_in = 1; 
    #2 comparator_in = 1; 
    #2 comparator_in = 1; 
    #2 comparator_in = 1; 
    #2 comparator_in = 1; 
    #2 comparator_in = 1; 
    #2 comparator_in = 1; 
    //averaging
    #2 comparator_in = 1; //0008
    #2 comparator_in = 1; 
    #2 comparator_in = 1; 
    #2 comparator_in = 1; 
    #2 comparator_in = 1; 
    #2 comparator_in = 1; 
    #2 comparator_in = 1; 
    #2 comparator_in = 1; 
    #2 comparator_in = 1; 
    #2 comparator_in = 1; 
    #2 comparator_in = 1; 
    #2 comparator_in = 1; 
    #2 comparator_in = 1; 
    #2 comparator_in = 1; 
    #2 comparator_in = 1; 
    #2 comparator_in = 1; 
    #2 comparator_in = 1; 
    #2 comparator_in = 1; 
    #2 comparator_in = 1; 
    #2 comparator_in = 1; 
    #2 comparator_in = 1; 
    #2 comparator_in = 1; 
    #2 comparator_in = 1; 
    #2 comparator_in = 1; 
    #2 comparator_in = 1; 
    #2 comparator_in = 1; 
    #2 comparator_in = 1; 
    #2 comparator_in = 1; 
    #2 comparator_in = 1; 
    #2 comparator_in = 1; 
    #2 comparator_in = 1; 
    //averaging
    #2 comparator_in = 1; //0004
    #2 comparator_in = 1; 
    #2 comparator_in = 1; 
    #2 comparator_in = 1; 
    #2 comparator_in = 1; 
    #2 comparator_in = 1; 
    #2 comparator_in = 1; 
    #2 comparator_in = 1; 
    #2 comparator_in = 1; 
    #2 comparator_in = 1; 
    #2 comparator_in = 1; 
    #2 comparator_in = 1; 
    #2 comparator_in = 1; 
    #2 comparator_in = 1; 
    #2 comparator_in = 1; 
    #2 comparator_in = 1; 
    #2 comparator_in = 1; 
    #2 comparator_in = 1; 
    #2 comparator_in = 1; 
    #2 comparator_in = 1; 
    #2 comparator_in = 1; 
    #2 comparator_in = 1; 
    #2 comparator_in = 1; 
    #2 comparator_in = 1; 
    #2 comparator_in = 1; 
    #2 comparator_in = 1; 
    #2 comparator_in = 1; 
    #2 comparator_in = 1; 
    #2 comparator_in = 1; 
    #2 comparator_in = 1; 
    #2 comparator_in = 1; 
    //averaging
    #2 comparator_in = 1; //0002
    #2 comparator_in = 1; 
    #2 comparator_in = 1; 
    #2 comparator_in = 1; 
    #2 comparator_in = 1; 
    #2 comparator_in = 1; 
    #2 comparator_in = 1; 
    #2 comparator_in = 1; 
    #2 comparator_in = 1; 
    #2 comparator_in = 1; 
    #2 comparator_in = 1; 
    #2 comparator_in = 1; 
    #2 comparator_in = 1; 
    #2 comparator_in = 1; 
    #2 comparator_in = 1; 
    #2 comparator_in = 1; 
    #2 comparator_in = 1; 
    #2 comparator_in = 1; 
    #2 comparator_in = 1; 
    #2 comparator_in = 1; 
    #2 comparator_in = 1; 
    #2 comparator_in = 1; 
    #2 comparator_in = 1; 
    #2 comparator_in = 1; 
    #2 comparator_in = 1; 
    #2 comparator_in = 1; 
    #2 comparator_in = 1; 
    #2 comparator_in = 1; 
    #2 comparator_in = 1; 
    #2 comparator_in = 1; 
    #2 comparator_in = 1; 



    //  sixth value zero without averaging
    avg_control = 3'b000; //0x averaging
    #2 comparator_in = 0; //0001
    #2 comparator_in = 0; //8000
    #2 comparator_in = 0; //4000
    #2 comparator_in = 0; //2000
    #2 comparator_in = 0; //1000
    #2 comparator_in = 0; //0800
    #2 comparator_in = 0; //0400
    #2 comparator_in = 0; //0200
    #2 comparator_in = 0; //0100
    #2 comparator_in = 0; //0080
    #2 comparator_in = 0; //0040
    #2 comparator_in = 0; //0020
    //averaging
    #2 comparator_in = 0; //0010
    //averaging
    #2 comparator_in = 0; //0008
    //averaging
    #2 comparator_in = 0; //0004
    //averaging
    #2 comparator_in = 0; //0002

    #512 $finish;
   end

    initial begin
   	#1 clk=0;
    #6 clk=0;
    forever begin
    	#1 clk = ~clk;
    end
    end  


endmodule

verilog/dump.vcd
$date
	Tue Oct  4 21:04:16 2022
$end
$version
	Icarus Verilog
$end
$timescale
	1us
$end
$scope module adc_control_nonbinary_tb $end
$var reg 1 ! clk $end
$upscope $end
$scope module adc_control_nonbinary_tb $end
$var reg 1 " rst $end
$upscope $end
$scope module adc_control_nonbinary_tb $end
$var reg 1 # comparator_in $end
$upscope $end
$scope module adc_control_nonbinary_tb $end
$var reg 3 $ avg_control [2:0] $end
$upscope $end
$scope module adc_control_nonbinary_tb $end
$var wire 1 % sample $end
$upscope $end
$scope module adc_control_nonbinary_tb $end
$var wire 1 & nsample $end
$upscope $end
$scope module adc_control_nonbinary_tb $end
$var wire 1 ' enable $end
$upscope $end
$scope module adc_control_nonbinary_tb $end
$var wire 1 ( conv_finished $end
$upscope $end
$scope module adc_control_nonbinary_tb $end
$var wire 12 ) p_switch [11:0] $end
$upscope $end
$scope module adc_control_nonbinary_tb $end
$var wire 12 * n_switch [11:0] $end
$upscope $end
$scope module adc_control_nonbinary_tb $end
$var wire 12 + result [11:0] $end
$upscope $end
$scope module adc_control_nonbinary_tb $end
$scope module testmodule $end
$var wire 3 , avg_control [2:0] $end
$var wire 1 ! clk $end
$var wire 1 # comparator_in $end
$var wire 1 & nsample $end
$var wire 1 " rst $end
$var wire 1 % sample $end
$var wire 1 ( conv_finished $end
$var parameter 32 - MATRIX_BITS $end
$var parameter 32 . NONBINARY_REDUNDANCY $end
$var reg 5 / average_count_limit [4:0] $end
$var reg 5 0 average_counter [4:0] $end
$var reg 1 1 average_result $end
$var reg 6 2 average_sum [5:0] $end
$var reg 1 3 averaging $end
$var reg 12 4 data_register [11:0] $end
$var reg 1 ' enable $end
$var reg 1 5 lsb_region $end
$var reg 12 6 n_switch [11:0] $end
$var reg 5 7 next_average_counter [4:0] $end
$var reg 6 8 next_average_sum [5:0] $end
$var reg 12 9 next_data_register [11:0] $end
$var reg 1 : next_enable $end
$var reg 12 ; next_result [11:0] $end
$var reg 3 < next_sampled_avg_control [2:0] $end
$var reg 16 = next_shift_register [15:0] $end
$var reg 12 > nonbinary_value [11:0] $end
$var reg 12 ? p_switch [11:0] $end
$var reg 12 @ result [11:0] $end
$var reg 3 A sampled_avg_control [2:0] $end
$var reg 16 B shift_register [15:0] $end
$upscope $end
$upscope $end
$enddefinitions $end
$comment Show the parameter values. $end
$dumpall
b11 .
b1100 -
$end
#0
$dumpvars
bx B
bx A
bx @
bx ?
bx >
bx =
bx <
bx ;
x:
bx 9
bx 8
bx 7
bx 6
x5
bx 4
x3
bx 2
x1
bx 0
bx /
bx ,
bx +
bx *
bx )
x(
x'
x&
x%
bx $
x#
x"
x!
$end
#10
0!
1"
#20
b111111111111 )
b111111111111 ?
b0 *
b0 6
b0 >
b1000000000000000 =
1:
b1 /
b0 ;
b0 9
b0x 8
b1 7
03
0&
05
1%
1(
b0 +
b0 @
0'
b1 B
b0 A
b0 4
b0 2
b1 0
0"
#30
1"
#40
b1 <
b1 $
b1 ,
#50
01
b0 8
0#
#80
b100011111111 )
b100011111111 ?
b11100000000 *
b11100000000 6
b11 /
b11100000000 >
b100000000000000 =
1&
0%
0(
b1 A
b1000000000000000 B
1'
1!
#90
b11100000000 9
11
b1 8
0!
1#
#100
b10000000000 >
b10000000000000 =
b101100000000 9
b10011111111 )
b10011111111 ?
b101100000000 *
b101100000000 6
b100000000000000 B
b11100000000 4
b1 2
1!
#110
b11100000000 9
01
b0 8
0!
0#
#120
b11011111111 )
b11011111111 ?
b100100000000 *
b100100000000 6
b1000000000 >
b1000000000000 =
b0 2
b10000000000000 B
1!
#130
0!
#140
b11110111111 )
b11110111111 ?
b100001000000 *
b100001000000 6
b101000000 >
b100000000000 =
b1000000000000 B
1!
#150
0!
#160
b100000111111 )
b100000111111 ?
b11111000000 *
b11111000000 6
b11000000 >
b10000000000 =
b100000000000 B
1!
#170
0!
#180
b100010011111 )
b100010011111 ?
b11101100000 *
b11101100000 6
b1100000 >
b1000000000 =
b10000000000 B
1!
#190
0!
#200
b100010111111 )
b100010111111 ?
b11101000000 *
b11101000000 6
b1000000 >
b100000000 =
b1000000000 B
1!
#210
0!
#220
b100011011111 )
b100011011111 ?
b11100100000 *
b11100100000 6
b100000 >
b10000000 =
b100000000 B
1!
#230
0!
#240
b100011100111 )
b100011100111 ?
b11100011000 *
b11100011000 6
b11000 >
b1000000 =
b10000000 B
1!
#250
0!
#260
b100011101111 )
b100011101111 ?
b11100010000 *
b11100010000 6
b10000 >
b100000 =
b1000000 B
1!
#270
0!
#280
b100011110101 )
b100011110101 ?
b11100001010 *
b11100001010 6
b1010 >
b10000 =
b100000 B
1!
#290
0!
#300
b10 7
b100011111001 )
b100011111001 ?
b11100000110 *
b11100000110 6
13
b110 >
b10000 =
15
b10000 B
1!
#310
0!
#320
b11 7
b10 0
1!
#330
0!
#340
b1000 =
b1 7
03
b11 0
1!
#350
0!
#360
b10 7
b100011111011 )
b100011111011 ?
b11100000100 *
b11100000100 6
13
b100 >
b1000 =
b1 0
b1000 B
1!
#370
0!
#380
b11 7
b10 0
1!
#390
0!
#400
b100 =
b1 7
03
b11 0
1!
#410
0!
#420
b10 7
b100011111101 )
b100011111101 ?
b11100000010 *
b11100000010 6
b10 >
b100 =
13
b100 B
b1 0
1!
#430
0!
#440
b11 7
b10 0
1!
#450
0!
#460
b10 =
b1 7
03
b11 0
1!
#470
0!
#480
b10 7
b100011111110 )
b100011111110 ?
b11100000001 *
b11100000001 6
13
b1 >
b0 ;
b10 =
1:
b1 0
b10 B
1!
#490
0!
#500
b11 7
b10 0
1!
#510
0!
#520
b11100000000 ;
b1 =
0:
b1 7
03
b11 0
1!
#530
0!
b0 $
b0 ,
#540
b100011111111 )
b100011111111 ?
b11100000000 *
b11100000000 6
b0 >
b0 9
b0 <
1:
b1000000000000000 =
03
0&
05
1%
1(
b11100000000 +
b11100000000 @
0'
b1 B
b1 0
1!
#550
0!
#560
b1 /
b11100000000 >
b100011111111 )
b100011111111 ?
b11100000000 *
b11100000000 6
b100000000000000 =
1&
0%
0(
b0 4
b0 A
b1000000000000000 B
1'
1!
#570
0!
#580
b101111111111 )
b101111111111 ?
b10000000000 *
b10000000000 6
b10000000000 >
b10000000000000 =
b100000000000000 B
1!
#590
b10000000000 9
11
b1 8
0!
1#
#600
b1000000000 >
b11000000000 9
b100111111111 )
b100111111111 ?
b11000000000 *
b11000000000 6
b1000000000000 =
b1 2
b10000000000 4
b10000000000000 B
1!
#610
b10000000000 9
01
b0 8
0!
0#
#620
b101010111111 )
b101010111111 ?
b10101000000 *
b10101000000 6
b101000000 >
b100000000000 =
b1000000000000 B
b0 2
1!
#630
0!
#640
b101100111111 )
b101100111111 ?
b10011000000 *
b10011000000 6
b11000000 >
b10000000000 =
b100000000000 B
1!
#650
0!
#660
b101110011111 )
b101110011111 ?
b10001100000 *
b10001100000 6
b1100000 >
b1000000000 =
b10000000000 B
1!
#670
0!
#680
b101110111111 )
b101110111111 ?
b10001000000 *
b10001000000 6
b1000000 >
b100000000 =
b1000000000 B
1!
#690
0!
#700
b101111011111 )
b101111011111 ?
b10000100000 *
b10000100000 6
b100000 >
b10000000 =
b100000000 B
1!
#710
0!
#720
b101111100111 )
b101111100111 ?
b10000011000 *
b10000011000 6
b11000 >
b1000000 =
b10000000 B
1!
#730
0!
#740
b101111101111 )
b101111101111 ?
b10000010000 *
b10000010000 6
b10000 >
b100000 =
b1000000 B
1!
#750
0!
#760
b101111110101 )
b101111110101 ?
b10000001010 *
b10000001010 6
b1010 >
b10000 =
b100000 B
1!
#770
0!
#780
b101111111001 )
b101111111001 ?
b10000000110 *
b10000000110 6
b110 >
b1000 =
15
b10000 B
1!
#790
0!
#800
b101111111011 )
b101111111011 ?
b10000000100 *
b10000000100 6
b100 >
b100 =
b1000 B
1!
#810
0!
#820
b101111111101 )
b101111111101 ?
b10000000010 *
b10000000010 6
b10 >
b10 =
b100 B
1!
#830
0!
#840
b101111111110 )
b101111111110 ?
b10000000001 *
b10000000001 6
b1 >
b10000000000 ;
0:
b1 =
b10 B
1!
#850
0!
#860
b101111111111 )
b101111111111 ?
b10000000000 *
b10000000000 6
b0 >
b0 9
b1000000000000000 =
1:
0&
05
1%
1(
b10000000000 +
b10000000000 @
0'
b1 B
1!
#870
0!
#880
b11100000000 >
b100011111111 )
b100011111111 ?
b11100000000 *
b11100000000 6
b100000000000000 =
1&
0%
0(
b0 4
b1000000000000000 B
1'
1!
#890
0!
#900
b101111111111 )
b101111111111 ?
b10000000000 *
b10000000000 6
b10000000000 >
b10000000000000 =
b100000000000000 B
1!
#910
0!
#920
b110111111111 )
b110111111111 ?
b1000000000 *
b1000000000 6
b1000000000 >
b1000000000000 =
b10000000000000 B
1!
#930
0!
#940
b111010111111 )
b111010111111 ?
b101000000 *
b101000000 6
b101000000 >
b100000000000 =
b1000000000000 B
1!
#950
0!
#960
b111100111111 )
b111100111111 ?
b11000000 *
b11000000 6
b11000000 >
b10000000000 =
b100000000000 B
1!
#970
0!
#980
b111110011111 )
b111110011111 ?
b1100000 *
b1100000 6
b1100000 >
b1000000000 =
b10000000000 B
1!
#990
0!
#1000
b111110111111 )
b111110111111 ?
b1000000 *
b1000000 6
b1000000 >
b100000000 =
b1000000000 B
1!
#1010
0!
#1020
b111111011111 )
b111111011111 ?
b100000 *
b100000 6
b100000 >
b10000000 =
b100000000 B
1!
#1030
0!
#1040
b111111100111 )
b111111100111 ?
b11000 *
b11000 6
b11000 >
b1000000 =
b10000000 B
1!
#1050
0!
#1060
b111111101111 )
b111111101111 ?
b10000 *
b10000 6
b10000 >
b100000 =
b1000000 B
1!
#1070
0!
#1080
b111111110101 )
b111111110101 ?
b1010 *
b1010 6
b1010 >
b10000 =
b100000 B
1!
#1090
0!
#1100
b111111111001 )
b111111111001 ?
b110 *
b110 6
b110 >
b1000 =
15
b10000 B
1!
#1110
b110 9
11
b1 8
0!
1#
#1120
b100 >
b1010 9
b111111110101 )
b111111110101 ?
b1010 *
b1010 6
b100 =
b1 2
b110 4
b1000 B
1!
#1130
0!
#1140
b10 >
b10 =
b1100 9
b111111110011 )
b111111110011 ?
b1100 *
b1100 6
b100 B
b1010 4
1!
#1150
0!
#1160
b1 >
b1101 ;
b1101 9
b111111110010 )
b111111110010 ?
b1101 *
b1101 6
0:
b1 =
b1100 4
b10 B
1!
#1170
0!
b10 $
b10 ,
#1180
b0 >
b10 <
b1000000000000000 =
1:
b0 9
b111111110010 )
b111111110010 ?
b1101 *
b1101 6
0&
05
1%
1(
b1101 +
b1101 @
0'
b1 B
b1101 4
1!
#1190
01
b0 8
0!
0#
#1200
b111 /
b11100000000 >
b100011111111 )
b100011111111 ?
b11100000000 *
b11100000000 6
b100000000000000 =
1&
0%
0(
b0 2
b0 4
b10 A
b1000000000000000 B
1'
1!
#1210
0!
#1220
b101111111111 )
b101111111111 ?
b10000000000 *
b10000000000 6
b10000000000 >
b10000000000000 =
b100000000000000 B
1!
#1230
0!
#1240
b110111111111 )
b110111111111 ?
b1000000000 *
b1000000000 6
b1000000000 >
b1000000000000 =
b10000000000000 B
1!
#1250
b1000000000 9
11
b1 8
0!
1#
#1260
b101000000 >
b100000000000 =
b1101000000 9
b110010111111 )
b110010111111 ?
b1101000000 *
b1101000000 6
b1000000000000 B
b1000000000 4
b1 2
1!
#1270
b1000000000 9
01
b0 8
0!
0#
#1280
b110100111111 )
b110100111111 ?
b1011000000 *
b1011000000 6
b11000000 >
b10000000000 =
b0 2
b100000000000 B
1!
#1290
0!
#1300
b110110011111 )
b110110011111 ?
b1001100000 *
b1001100000 6
b1100000 >
b1000000000 =
b10000000000 B
1!
#1310
0!
#1320
b110110111111 )
b110110111111 ?
b1001000000 *
b1001000000 6
b1000000 >
b100000000 =
b1000000000 B
1!
#1330
0!
#1340
b110111011111 )
b110111011111 ?
b1000100000 *
b1000100000 6
b100000 >
b10000000 =
b100000000 B
1!
#1350
0!
#1360
b110111100111 )
b110111100111 ?
b1000011000 *
b1000011000 6
b11000 >
b1000000 =
b10000000 B
1!
#1370
0!
#1380
b110111101111 )
b110111101111 ?
b1000010000 *
b1000010000 6
b10000 >
b100000 =
b1000000 B
1!
#1390
0!
#1400
b110111110101 )
b110111110101 ?
b1000001010 *
b1000001010 6
b1010 >
b10000 =
b100000 B
1!
#1410
0!
