verilog/adc_control/define.vh
module globals ();

   //Dimensions of the cap-matrix
   parameter MATRIX_ROWS = 16;
   parameter MATRIX_COLS = 32;
   parameter MATRIX_BINS = 3;
   parameter MATRIX_BITS = 12;


   parameter NONBINARY_LUT_WIDTH = 14;

   parameter OSR_BITS = 4;
   parameter RESULT_BITS     = MATRIX_BITS;
   parameter RESULT_OSR_BITS = MATRIX_BITS + OSR_BITS;

endmodule

verilog/adc_control_nonbinary.v
`default_nettype none
//`include "define.vh"

//  Copyright 2022 Manuel Moser
//
//   Licensed under the Apache License, Version 2.0 (the "License");
//   you may not use this file except in compliance with the License.
//   You may obtain a copy of the License at
//
//       http://www.apache.org/licenses/LICENSE-2.0
//
//   Unless required by applicable law or agreed to in writing, software
//   distributed under the License is distributed on an "AS IS" BASIS,
//   WITHOUT WARRANTIES OR CONDITIONS OF ANY KIND, either express or implied.
//   See the License for the specific language governing permissions and
//   limitations under the License.


// Top module ADC Control
module adc_control_nonbinary #(parameter MATRIX_BITS = 12, NONBINARY_REDUNDANCY = 3)(
   input wire clk,
   input wire nrst,
   input wire comparator_in,
   input wire [2:0] avg_control,
   output wire sample,
   output wire nsample,
   output wire enable,
   output wire conv_finished,
   output wire[MATRIX_BITS-1:0]  p_switch,
   output wire[MATRIX_BITS-1:0]  n_switch,
   output reg[MATRIX_BITS-1:0]   result
   );

   // Synchronous data registers
   wire [MATRIX_BITS-1:0] next_result;
   wire [4:0] next_average_counter;
   wire [5:0] next_average_sum;
   wire [2:0] next_sampled_avg_control;
   wire [MATRIX_BITS+NONBINARY_REDUNDANCY:0] next_shift_register;
   wire [MATRIX_BITS-1:0] next_data_register;
   
   // Average calculation registers in LSB region
   reg [4:0] average_counter;
   wire [4:0] average_count_limit;
   reg [5:0] average_sum;
   wire averaged_comparator_in;
   reg [2:0] sampled_avg_control;
   
   // State-Machine Shift Register
   reg [MATRIX_BITS+NONBINARY_REDUNDANCY:0] shift_register;
   reg [MATRIX_BITS-1:0] data_register;
   reg [MATRIX_BITS-1:0] nonbinary_value;

   // states of the machine
   wire is_sampling; 
   assign is_sampling = shift_register[0];
   wire lsb_region;
   assign lsb_region  = (shift_register[1] | shift_register[2] | shift_register[3] | shift_register[4]);
   wire is_averaging; 
   assign is_averaging = (lsb_region && (average_counter < average_count_limit));
   wire conversion_ending;
   assign conversion_ending = ((shift_register[1]==1'b1)&~is_averaging);

   // direct output of internal states
   assign sample = is_sampling;
   assign nsample = ~is_sampling;
   assign conv_finished = is_sampling;
   assign enable = ~is_sampling;
   assign n_switch = data_register + nonbinary_value;
   assign p_switch = ~(data_register + nonbinary_value);

    //******************************************
    //   Synchronous process and Reset Handling
    //******************************************
   always @(posedge clk, negedge nrst) begin
      if (nrst == 1'b0) begin  
         result    <= {MATRIX_BITS{1'b0}};
         shift_register <= {{(MATRIX_BITS+NONBINARY_REDUNDANCY){1'b0}},1'b1};     
         sampled_avg_control <= 3'b000;   
         average_counter <= 5'd1;
         average_sum     <= 5'd0;
         data_register <= {MATRIX_BITS{1'b0}}; 
      end 
      else begin	
         result              <= next_result;
         shift_register      <= next_shift_register; 
         sampled_avg_control <= next_sampled_avg_control; 
         average_counter     <= next_average_counter;
         average_sum         <= next_average_sum;
         data_register       <= next_data_register;
      end
   end 

    //*******************************
    //   Combinatorial Processes
    //*******************************
   assign next_shift_register = is_averaging ? shift_register : {shift_register[0],shift_register[MATRIX_BITS+NONBINARY_REDUNDANCY:1]};
   assign next_sampled_avg_control = is_sampling ? avg_control : sampled_avg_control;
   assign next_data_register = is_sampling    ? {MATRIX_BITS{1'b0}} :
                               averaged_comparator_in ? data_register+nonbinary_value: 
                                                data_register;
   
   assign next_result = conversion_ending ? next_data_register : result;
   
   // Handling of Averaging Counter, Sum and Result
   // While averaging, count up and preserve the last result.
   // Wnen averaging is done and in lsb_region, then update the result and reset the counter.
   // Else reset values in registers
   assign next_average_counter = is_averaging ? average_counter+1 : 5'd1;
   assign next_average_sum     = is_averaging ? average_sum+comparator_in : {4'b0000, comparator_in};

   assign averaged_comparator_in = (~lsb_region) ? comparator_in :
                                   is_averaging ? 1'b0 :
                                   (sampled_avg_control ==  3'b001) ? average_sum[1] :
                                   (sampled_avg_control ==  3'b010) ? average_sum[2] :
                                   (sampled_avg_control ==  3'b011) ? average_sum[3] :
                                   (sampled_avg_control ==  3'b100) ? average_sum[4] :
                                   comparator_in;


   //*******************************
   //   NONBINARY Lookuptable
   //*******************************
   // Lookuptable for Nonbinary-Values
   // for 12 Bit Matrix + 3 redundant Bits
   always @(*) begin
      casex (shift_register)
         16'd2**0:  nonbinary_value <= 12'd0; 
         16'd2**15: nonbinary_value <= 12'd2048; 
         16'd2**14: nonbinary_value <= 12'd806; 
         16'd2**13: nonbinary_value <= 12'd486; 
         16'd2**12: nonbinary_value <= 12'd295; 
         16'd2**11: nonbinary_value <= 12'd180; 
         16'd2**10: nonbinary_value <= 12'd110; 
         16'd2**9:  nonbinary_value <= 12'd67; 
         16'd2**8:  nonbinary_value <= 12'd41; 
         16'd2**7:  nonbinary_value <= 12'd25; 
         16'd2**6:  nonbinary_value <= 12'd15; 
         16'd2**5:  nonbinary_value <= 12'd9; 
         16'd2**4:  nonbinary_value <= 12'd6; 
         16'd2**3:  nonbinary_value <= 12'd4; 
         16'd2**2:  nonbinary_value <= 12'd2; 
         16'd2**1:  nonbinary_value <= 12'd1; 
         default:   nonbinary_value <= 12'dx;
      endcase
    end 

    //*******************************
    //   AVERAGING lookup table
    //*******************************
    // Decide how often comparator_in should be sampled.
    // Default is 1 sample per 1 decision, 
    // max. is 31 samples for 1 decision
    assign average_count_limit = (sampled_avg_control == 3'b001) ? 5'd3 :
                                  (sampled_avg_control == 3'b010) ? 5'd7 :
                                  (sampled_avg_control == 3'b011) ? 5'd15 :
                                  (sampled_avg_control == 3'b100) ? 5'd31 :
                                  5'd1;
    
endmodule

verilog/adc_control_nonbinary_tb.v
//  Copyright 2022 Manuel Moser
//
//   Licensed under the Apache License, Version 2.0 (the "License");
//   you may not use this file except in compliance with the License.
//   You may obtain a copy of the License at
//
//       http://www.apache.org/licenses/LICENSE-2.0
//
//   Unless required by applicable law or agreed to in writing, software
//   distributed under the License is distributed on an "AS IS" BASIS,
//   WITHOUT WARRANTIES OR CONDITIONS OF ANY KIND, either express or implied.
//   See the License for the specific language governing permissions and
//   limitations under the License.

`include "adc_control_nonbinary.v"
`timescale 10us/1us

module adc_control_nonbinary_tb;
  parameter MATRIX_BITS = 12;
  reg clk;
  reg nrst;
  reg comparator_in;
  reg [2:0] avg_control;
  wire sample;
  wire nsample;
  wire enable;
  wire conv_finished;
  wire[MATRIX_BITS-1:0]  p_switch;
  wire[MATRIX_BITS-1:0]  n_switch;
  wire[MATRIX_BITS-1:0]  result;

  adc_control_nonbinary testmodule (
	   .clk(clk),
	   .nrst(nrst),
	   .comparator_in(comparator_in),
	   .avg_control(avg_control),
	   .sample(sample),
	   .nsample(nsample),
	   .enable(enable),
	   .conv_finished(conv_finished),
	   .p_switch(p_switch),
	   .n_switch(n_switch),
	   .result(result)
	   );	

   initial begin
   	$dumpfile("dump.vcd");
   	$dumpvars(0,
   		clk,
   		nrst,
   		comparator_in,
   		avg_control,
   		sample,
   		nsample,
   		enable,
   		conv_finished,
   		p_switch,
   		n_switch,
   		result,
   		testmodule);
   end
   
   initial begin
   	#1 nrst=1;
    #1 nrst=0;
    #1 nrst=1;
    #1 nrst=1; avg_control = 3'b001;
    #1 comparator_in = 0;

    // first value is d2048
    avg_control = 3'b001; //4x averaging    
    #2 comparator_in = 0; //0001
    #2 comparator_in = 1; //8000
    #2 comparator_in = 0; //4000
    #2 comparator_in = 0; //2000
    #2 comparator_in = 0; //1000
    #2 comparator_in = 0; //0800
    #2 comparator_in = 0; //0400
    #2 comparator_in = 0; //0200
    #2 comparator_in = 0; //0100
    #2 comparator_in = 0; //0080
    #2 comparator_in = 0; //0040
    #2 comparator_in = 0; //0020
    //averaging
    #2 comparator_in = 0; //0010
    #2 comparator_in = 0;
    #2 comparator_in = 0;
    //averaging
    #2 comparator_in = 0; //0008
    #2 comparator_in = 0;
    #2 comparator_in = 0;
    //averaging
    #2 comparator_in = 0; //0004
    #2 comparator_in = 0;
    #2 comparator_in = 0;
    //averaging
    #2 comparator_in = 0; //0002
    #2 comparator_in = 0;
    #2 comparator_in = 0;
        

    // second value is d806
    avg_control = 3'b000; //0x averaging
    #2 comparator_in = 0; //0001
    #2 comparator_in = 0; //8000
    #2 comparator_in = 1; //4000 +806
    #2 comparator_in = 0; //2000
    #2 comparator_in = 0; //1000
    #2 comparator_in = 0; //0800
    #2 comparator_in = 0; //0400
    #2 comparator_in = 0; //0200
    #2 comparator_in = 0; //0100
    #2 comparator_in = 0; //0080
    #2 comparator_in = 0; //0040
    #2 comparator_in = 0; //0020
    //averaging
    #2 comparator_in = 0; //0010
    //averaging
    #2 comparator_in = 0; //0008
    //averaging
    #2 comparator_in = 0; //0004
    //averaging
    #2 comparator_in = 0; //0002
    
    // third value is d13
    avg_control = 3'b000; //0x averaging
    #2 comparator_in = 0; //0001
    #2 comparator_in = 0; //8000
    #2 comparator_in = 0; //4000
    #2 comparator_in = 0; //2000
    #2 comparator_in = 0; //1000
    #2 comparator_in = 0; //0800
    #2 comparator_in = 0; //0400
    #2 comparator_in = 0; //0200
    #2 comparator_in = 0; //0100
    #2 comparator_in = 0; //0080
    #2 comparator_in = 0; //0040
    #2 comparator_in = 0; //0020
    //averaging
    #2 comparator_in = 1; //0010 +6
    //averaging
    #2 comparator_in = 1; //0008 +4
    //averaging
    #2 comparator_in = 1; //0004 +2
    //averaging
    #2 comparator_in = 1; //0002 +1

    // fourth value is d489
    avg_control = 3'b010; //8x averaging
    #2 comparator_in = 0; //0001
    #2 comparator_in = 0; //8000
    #2 comparator_in = 0; //4000
    #2 comparator_in = 1; //2000 +486
    #2 comparator_in = 0; //1000
    #2 comparator_in = 0; //0800
    #2 comparator_in = 0; //0400
    #2 comparator_in = 0; //0200
    #2 comparator_in = 0; //0100
    #2 comparator_in = 0; //0080
    #2 comparator_in = 0; //0040
    #2 comparator_in = 0; //0020
    //averaging
    #2 comparator_in = 0; //0010
    #2 comparator_in = 1; 
    #2 comparator_in = 0; 
    #2 comparator_in = 1; 
    #2 comparator_in = 0; 
    #2 comparator_in = 0; 
    #2 comparator_in = 0; 
    //averaging
    #2 comparator_in = 0; //0008
    #2 comparator_in = 0; 
    #2 comparator_in = 0;
    #2 comparator_in = 0; 
    #2 comparator_in = 0; 
    #2 comparator_in = 0; 
    #2 comparator_in = 1; 
    //averaging
    #2 comparator_in = 1; //0010 +2
    #2 comparator_in = 0; 
    #2 comparator_in = 0;
    #2 comparator_in = 1; 
    #2 comparator_in = 0; 
    #2 comparator_in = 1; 
    #2 comparator_in = 1; 
    //averaging
    #2 comparator_in = 1; //0010 +1
    #2 comparator_in = 1; 
    #2 comparator_in = 1; 
    #2 comparator_in = 1; 
    #2 comparator_in = 1; 
    #2 comparator_in = 1; 
    #2 comparator_in = 1; 
    

    // fifth value is max value with max averaging d4095
    avg_control = 3'b100; //0x averaging
    #2 comparator_in = 0; //0001
    #2 comparator_in = 1; //8000
    #2 comparator_in = 1; //4000
    #2 comparator_in = 1; //2000
    #2 comparator_in = 1; //1000
    #2 comparator_in = 1; //0800
    #2 comparator_in = 1; //0400
    #2 comparator_in = 1; //0200
    #2 comparator_in = 1; //0100
    #2 comparator_in = 1; //0080
    #2 comparator_in = 1; //0040
    #2 comparator_in = 1; //0020
    //averaging
    #2 comparator_in = 1; //0010
    #2 comparator_in = 1; 
    #2 comparator_in = 1; 
    #2 comparator_in = 1; 
    #2 comparator_in = 1; 
    #2 comparator_in = 1; 
    #2 comparator_in = 1; 
    #2 comparator_in = 1; 
    #2 comparator_in = 1; 
    #2 comparator_in = 1; 
    #2 comparator_in = 1; 
    #2 comparator_in = 1; 
    #2 comparator_in = 1; 
    #2 comparator_in = 1; 
    #2 comparator_in = 1; 
    #2 comparator_in = 1; 
    #2 comparator_in = 1; 
    #2 comparator_in = 1; 
    #2 comparator_in = 1; 
    #2 comparator_in = 1; 
    #2 comparator_in = 1; 
    #2 comparator_in = 1; 
    #2 comparator_in = 1; 
    #2 comparator_in = 1; 
    #2 comparator_in = 1; 
    #2 comparator_in = 1; 
    #2 comparator_in = 1; 
    #2 comparator_in = 1; 
    #2 comparator_in = 1; 
    #2 comparator_in = 1; 
    #2 comparator_in = 1; 
    //averaging
    #2 comparator_in = 1; //0008
    #2 comparator_in = 1; 
    #2 comparator_in = 1; 
    #2 comparator_in = 1; 
    #2 comparator_in = 1; 
    #2 comparator_in = 1; 
    #2 comparator_in = 1; 
    #2 comparator_in = 1; 
    #2 comparator_in = 1; 
    #2 comparator_in = 1; 
    #2 comparator_in = 1; 
    #2 comparator_in = 1; 
    #2 comparator_in = 1; 
    #2 comparator_in = 1; 
    #2 comparator_in = 1; 
    #2 comparator_in = 1; 
    #2 comparator_in = 1; 
    #2 comparator_in = 1; 
    #2 comparator_in = 1; 
    #2 comparator_in = 1; 
    #2 comparator_in = 1; 
    #2 comparator_in = 1; 
    #2 comparator_in = 1; 
    #2 comparator_in = 1; 
    #2 comparator_in = 1; 
    #2 comparator_in = 1; 
    #2 comparator_in = 1; 
    #2 comparator_in = 1; 
    #2 comparator_in = 1; 
    #2 comparator_in = 1; 
    #2 comparator_in = 1; 
    //averaging
    #2 comparator_in = 1; //0004
    #2 comparator_in = 1; 
    #2 comparator_in = 1; 
    #2 comparator_in = 1; 
    #2 comparator_in = 1; 
    #2 comparator_in = 1; 
    #2 comparator_in = 1; 
    #2 comparator_in = 1; 
    #2 comparator_in = 1; 
    #2 comparator_in = 1; 
    #2 comparator_in = 1; 
    #2 comparator_in = 1; 
    #2 comparator_in = 1; 
    #2 comparator_in = 1; 
    #2 comparator_in = 1; 
    #2 comparator_in = 1; 
    #2 comparator_in = 1; 
    #2 comparator_in = 1; 
    #2 comparator_in = 1; 
    #2 comparator_in = 1; 
    #2 comparator_in = 1; 
    #2 comparator_in = 1; 
    #2 comparator_in = 1; 
    #2 comparator_in = 1; 
    #2 comparator_in = 1; 
    #2 comparator_in = 1; 
    #2 comparator_in = 1; 
    #2 comparator_in = 1; 
    #2 comparator_in = 1; 
    #2 comparator_in = 1; 
    #2 comparator_in = 1; 
    //averaging
    #2 comparator_in = 1; //0002
    #2 comparator_in = 1; 
    #2 comparator_in = 1; 
    #2 comparator_in = 1; 
    #2 comparator_in = 1; 
    #2 comparator_in = 1; 
    #2 comparator_in = 1; 
    #2 comparator_in = 1; 
    #2 comparator_in = 1; 
    #2 comparator_in = 1; 
    #2 comparator_in = 1; 
    #2 comparator_in = 1; 
    #2 comparator_in = 1; 
    #2 comparator_in = 1; 
    #2 comparator_in = 1; 
    #2 comparator_in = 1; 
    #2 comparator_in = 1; 
    #2 comparator_in = 1; 
    #2 comparator_in = 1; 
    #2 comparator_in = 1; 
    #2 comparator_in = 1; 
    #2 comparator_in = 1; 
    #2 comparator_in = 1; 
    #2 comparator_in = 1; 
    #2 comparator_in = 1; 
    #2 comparator_in = 1; 
    #2 comparator_in = 1; 
    #2 comparator_in = 1; 
    #2 comparator_in = 1; 
    #2 comparator_in = 1; 
    #2 comparator_in = 1; 



    //  sixth value zero without averaging
    avg_control = 3'b000; //0x averaging
    #2 comparator_in = 0; //0001
    #2 comparator_in = 0; //8000
    #2 comparator_in = 0; //4000
    #2 comparator_in = 0; //2000
    #2 comparator_in = 0; //1000
    #2 comparator_in = 0; //0800
    #2 comparator_in = 0; //0400
    #2 comparator_in = 0; //0200
    #2 comparator_in = 0; //0100
    #2 comparator_in = 0; //0080
    #2 comparator_in = 0; //0040
    #2 comparator_in = 0; //0020
    //averaging
    #2 comparator_in = 0; //0010
    //averaging
    #2 comparator_in = 0; //0008
    //averaging
    #2 comparator_in = 0; //0004
    //averaging
    #2 comparator_in = 0; //0002

    #512 $finish;
   end

    initial begin
   	#1 clk=0;
    #6 clk=0;
    forever begin
    	#1 clk = ~clk;
    end
    end  


endmodule

verilog/dump.vcd
$date
	Fri Oct 14 14:50:57 2022
$end
$version
	Icarus Verilog
$end
$timescale
	1us
$end
$scope module adc_control_nonbinary_tb $end
$var reg 1 ! clk $end
$upscope $end
$scope module adc_control_nonbinary_tb $end
$var reg 1 " nrst $end
$upscope $end
$scope module adc_control_nonbinary_tb $end
$var reg 1 # comparator_in $end
$upscope $end
$scope module adc_control_nonbinary_tb $end
$var reg 3 $ avg_control [2:0] $end
$upscope $end
$scope module adc_control_nonbinary_tb $end
$var wire 1 % sample $end
$upscope $end
$scope module adc_control_nonbinary_tb $end
$var wire 1 & nsample $end
$upscope $end
$scope module adc_control_nonbinary_tb $end
$var wire 1 ' enable $end
$upscope $end
$scope module adc_control_nonbinary_tb $end
$var wire 1 ( conv_finished $end
$upscope $end
$scope module adc_control_nonbinary_tb $end
$var wire 12 ) p_switch [11:0] $end
$upscope $end
$scope module adc_control_nonbinary_tb $end
$var wire 12 * n_switch [11:0] $end
$upscope $end
$scope module adc_control_nonbinary_tb $end
$var wire 12 + result [11:0] $end
$upscope $end
$scope module adc_control_nonbinary_tb $end
$scope module testmodule $end
$var wire 3 , avg_control [2:0] $end
$var wire 1 ! clk $end
$var wire 1 # comparator_in $end
$var wire 1 ( conv_finished $end
$var wire 1 - conversion_ending $end
$var wire 1 ' enable $end
$var wire 1 . is_averaging $end
$var wire 1 / lsb_region $end
$var wire 1 " nrst $end
$var wire 1 & nsample $end
$var wire 12 0 p_switch [11:0] $end
$var wire 1 % sample $end
$var wire 16 1 next_shift_register [15:0] $end
$var wire 3 2 next_sampled_avg_control [2:0] $end
$var wire 12 3 next_result [11:0] $end
$var wire 12 4 next_data_register [11:0] $end
$var wire 6 5 next_average_sum [5:0] $end
$var wire 5 6 next_average_counter [4:0] $end
$var wire 12 7 n_switch [11:0] $end
$var wire 1 8 is_sampling $end
$var wire 1 9 averaged_comparator_in $end
$var wire 5 : average_count_limit [4:0] $end
$var parameter 32 ; MATRIX_BITS $end
$var parameter 32 < NONBINARY_REDUNDANCY $end
$var reg 5 = average_counter [4:0] $end
$var reg 6 > average_sum [5:0] $end
$var reg 12 ? data_register [11:0] $end
$var reg 12 @ nonbinary_value [11:0] $end
$var reg 12 A result [11:0] $end
$var reg 3 B sampled_avg_control [2:0] $end
$var reg 16 C shift_register [15:0] $end
$upscope $end
$upscope $end
$enddefinitions $end
$comment Show the parameter values. $end
$dumpall
b11 <
b1100 ;
$end
#0
$dumpvars
bx C
bx B
bx A
bx @
bx ?
bx >
bx =
bx1 :
x9
x8
bx 7
bx 6
bx 5
bx 4
bx 3
bx 2
bx 1
bx 0
x/
x.
x-
bx ,
bx +
bx *
bx )
x(
x'
x&
x%
bx $
x#
x"
x!
$end
#10
0!
1"
#20
b111111111111 )
b111111111111 0
b0 *
b0 7
b0 @
0/
b0x 5
b0 3
0-
0.
b0 4
0'
0&
b1000000000000000 1
b1 6
b1 :
1(
1%
18
b0 ?
b0 >
b1 =
b0 B
b1 C
b0 +
b0 A
0"
#30
1"
#40
b1 2
b1 $
b1 ,
#50
b0 5
09
0#
#80
b11111111111 )
b11111111111 0
b100000000000 *
b100000000000 7
b100000000000 @
1'
1&
b100000000000000 1
b11 :
0(
0%
08
b1 B
b1000000000000000 C
1!
#90
b100000000000 4
b1 5
19
0!
1#
#100
b1100100110 @
b101100100110 4
b10000000000000 1
b10011011001 )
b10011011001 0
b101100100110 *
b101100100110 7
b100000000000 ?
b1 >
b100000000000000 C
1!
#110
b100000000000 4
b0 5
09
0!
0#
#120
b11000011001 )
b11000011001 0
b100111100110 *
b100111100110 7
b111100110 @
b1000000000000 1
b0 >
b10000000000000 C
1!
#130
0!
#140
b11011011000 )
b11011011000 0
b100100100111 *
b100100100111 7
b100100111 @
b100000000000 1
b1000000000000 C
1!
#150
0!
#160
b11101001011 )
b11101001011 0
b100010110100 *
b100010110100 7
b10110100 @
b10000000000 1
b100000000000 C
1!
#170
0!
#180
b11110010001 )
b11110010001 0
b100001101110 *
b100001101110 7
b1101110 @
b1000000000 1
b10000000000 C
1!
#190
0!
#200
b11110111100 )
b11110111100 0
b100001000011 *
b100001000011 7
b1000011 @
b100000000 1
b1000000000 C
1!
#210
0!
#220
b11111010110 )
b11111010110 0
b100000101001 *
b100000101001 7
b101001 @
b10000000 1
b100000000 C
1!
#230
0!
#240
b11111100110 )
b11111100110 0
b100000011001 *
b100000011001 7
b11001 @
b1000000 1
b10000000 C
1!
#250
0!
#260
b11111110000 )
b11111110000 0
b100000001111 *
b100000001111 7
b1111 @
b100000 1
b1000000 C
1!
#270
0!
#280
b11111110110 )
b11111110110 0
b100000001001 *
b100000001001 7
b1001 @
b10000 1
b100000 C
1!
#290
0!
#300
b11111111001 )
b11111111001 0
b100000000110 *
b100000000110 7
b110 @
b10 6
1.
1/
b10000 1
b10000 C
1!
#310
0!
#320
b11 6
b10 =
1!
#330
0!
#340
b1000 1
0.
b1 6
b11 =
1!
#350
0!
#360
b11111111011 )
b11111111011 0
b100000000100 *
b100000000100 7
b100 @
b1000 1
b10 6
1/
1.
b1 =
b1000 C
1!
#370
0!
#380
b11 6
b10 =
1!
#390
0!
#400
b100 1
0.
b1 6
b11 =
1!
#410
0!
#420
b11111111101 )
b11111111101 0
b100000000010 *
b100000000010 7
b10 @
b100 1
1/
b10 6
1.
b1 =
b100 C
1!
#430
0!
#440
b11 6
b10 =
1!
#450
0!
#460
b10 1
0.
b1 6
b11 =
1!
#470
0!
#480
b11111111110 )
b11111111110 0
b100000000001 *
b100000000001 7
b1 @
b10 6
1.
b1 =
b10 C
1!
#490
0!
#500
b11 6
b10 =
1!
#510
0!
#520
b100000000000 3
1-
b1 1
0.
b1 6
b11 =
1!
#530
0!
b0 $
b0 ,
#540
b11111111111 )
b11111111111 0
b100000000000 *
b100000000000 7
b0 @
b1000000000000000 1
0/
0-
b1 6
b0 2
b0 4
0'
0&
0.
1(
1%
18
b1 =
b1 C
b100000000000 +
b100000000000 A
1!
#550
0!
#560
b100000000000 @
1'
1&
b100000000000000 1
b11111111111 )
b11111111111 0
b1 :
0(
0%
08
b100000000000 *
b100000000000 7
b0 ?
b0 B
b1000000000000000 C
1!
#570
0!
#580
b110011011001 )
b110011011001 0
b1100100110 *
b1100100110 7
b1100100110 @
b10000000000000 1
b100000000000000 C
1!
#590
b1100100110 4
b1 5
19
0!
1#
#600
b111100110 @
b10100001100 4
b1000000000000 1
b101011110011 )
b101011110011 0
b10100001100 *
b10100001100 7
b1100100110 ?
b1 >
b10000000000000 C
1!
#610
b1100100110 4
b0 5
09
0!
0#
#620
b101110110010 )
b101110110010 0
b10001001101 *
b10001001101 7
b100100111 @
b100000000000 1
b0 >
b1000000000000 C
1!
#630
0!
#640
b110000100101 )
b110000100101 0
b1111011010 *
b1111011010 7
b10110100 @
b10000000000 1
b100000000000 C
1!
#650
0!
#660
b110001101011 )
b110001101011 0
b1110010100 *
b1110010100 7
b1101110 @
b1000000000 1
b10000000000 C
1!
#670
0!
#680
b110010010110 )
b110010010110 0
b1101101001 *
b1101101001 7
b1000011 @
b100000000 1
b1000000000 C
1!
#690
0!
#700
b110010110000 )
b110010110000 0
b1101001111 *
b1101001111 7
b101001 @
b10000000 1
b100000000 C
1!
#710
0!
#720
b110011000000 )
b110011000000 0
b1100111111 *
b1100111111 7
b11001 @
b1000000 1
b10000000 C
1!
#730
0!
#740
b110011001010 )
b110011001010 0
b1100110101 *
b1100110101 7
b1111 @
b100000 1
b1000000 C
1!
#750
0!
#760
b110011010000 )
b110011010000 0
b1100101111 *
b1100101111 7
b1001 @
b10000 1
b100000 C
1!
#770
0!
#780
b110011010011 )
b110011010011 0
b1100101100 *
b1100101100 7
b110 @
1/
b1000 1
b10000 C
1!
#790
0!
#800
b110011010101 )
b110011010101 0
b1100101010 *
b1100101010 7
b100 @
1/
b100 1
b1000 C
1!
#810
0!
#820
b110011010111 )
b110011010111 0
b1100101000 *
b1100101000 7
b10 @
1/
b10 1
b100 C
1!
#830
0!
#840
b110011011000 )
b110011011000 0
b1100100111 *
b1100100111 7
b1 @
b1100100110 3
1-
b1 1
b10 C
1!
#850
0!
#860
b110011011001 )
b110011011001 0
b1100100110 *
b1100100110 7
b0 @
0/
0-
b0 4
0'
0&
b1000000000000000 1
1(
1%
18
b1 C
b1100100110 +
b1100100110 A
1!
#870
0!
#880
b100000000000 @
1'
1&
b100000000000000 1
b11111111111 )
b11111111111 0
0(
0%
08
b100000000000 *
b100000000000 7
b0 ?
b1000000000000000 C
1!
#890
0!
#900
b110011011001 )
b110011011001 0
b1100100110 *
b1100100110 7
b1100100110 @
b10000000000000 1
b100000000000000 C
1!
#910
0!
#920
b111000011001 )
b111000011001 0
b111100110 *
b111100110 7
b111100110 @
b1000000000000 1
b10000000000000 C
1!
#930
0!
#940
b111011011000 )
b111011011000 0
b100100111 *
b100100111 7
b100100111 @
b100000000000 1
b1000000000000 C
1!
#950
0!
#960
b111101001011 )
b111101001011 0
b10110100 *
b10110100 7
b10110100 @
b10000000000 1
b100000000000 C
1!
#970
0!
#980
b111110010001 )
b111110010001 0
b1101110 *
b1101110 7
b1101110 @
b1000000000 1
b10000000000 C
1!
#990
0!
#1000
b111110111100 )
b111110111100 0
b1000011 *
b1000011 7
b1000011 @
b100000000 1
b1000000000 C
1!
#1010
0!
#1020
b111111010110 )
b111111010110 0
b101001 *
b101001 7
b101001 @
b10000000 1
b100000000 C
1!
#1030
0!
#1040
b111111100110 )
b111111100110 0
b11001 *
b11001 7
b11001 @
b1000000 1
b10000000 C
1!
#1050
0!
#1060
b111111110000 )
b111111110000 0
b1111 *
b1111 7
b1111 @
b100000 1
b1000000 C
1!
#1070
0!
#1080
b111111110110 )
b111111110110 0
b1001 *
b1001 7
b1001 @
b10000 1
b100000 C
1!
#1090
0!
#1100
b111111111001 )
b111111111001 0
b110 *
b110 7
b110 @
1/
b1000 1
b10000 C
1!
#1110
b110 4
19
b1 5
0!
1#
#1120
b100 @
b1010 4
1/
b100 1
b111111110101 )
b111111110101 0
b1010 *
b1010 7
b110 ?
b1 >
b1000 C
1!
#1130
0!
#1140
b10 @
1/
b1100 4
b10 1
b111111110011 )
b111111110011 0
b1100 *
b1100 7
b1010 ?
b100 C
1!
#1150
0!
#1160
b1 @
b1101 3
1-
b1101 4
b1 1
b111111110010 )
b111111110010 0
b1101 *
b1101 7
b1100 ?
b10 C
1!
#1170
0!
b10 $
b10 ,
#1180
b0 @
0/
0-
b10 2
b0 4
0'
0&
b1000000000000000 1
b111111110010 )
b111111110010 0
1(
1%
18
b1101 *
b1101 7
b1101 ?
b1 C
b1101 +
b1101 A
1!
#1190
b0 5
09
0!
0#
#1200
b100000000000 @
b111 :
1'
1&
b100000000000000 1
b11111111111 )
b11111111111 0
0(
0%
08
b100000000000 *
b100000000000 7
b0 ?
b0 >
b10 B
b1000000000000000 C
1!
#1210
0!
#1220
b110011011001 )
b110011011001 0
b1100100110 *
b1100100110 7
b1100100110 @
b10000000000000 1
b100000000000000 C
1!
#1230
0!
#1240
b111000011001 )
b111000011001 0
b111100110 *
b111100110 7
b111100110 @
b1000000000000 1
b10000000000000 C
1!
#1250
b111100110 4
b1 5
19
0!
1#
#1260
b100100111 @
b1100001101 4
b100000000000 1
b110011110010 )
b110011110010 0
b1100001101 *
b1100001101 7
b111100110 ?
b1 >
b1000000000000 C
1!
#1270
b111100110 4
b0 5
09
0!
0#
#1280
b110101100101 )
b110101100101 0
b1010011010 *
b1010011010 7
b10110100 @
b10000000000 1
b0 >
b100000000000 C
1!
#1290
0!
#1300
b110110101011 )
b110110101011 0
b1001010100 *
b1001010100 7
b1101110 @
b1000000000 1
b10000000000 C
1!
#1310
0!
#1320
b110111010110 )
b110111010110 0
b1000101001 *
b1000101001 7
b1000011 @
b100000000 1
b1000000000 C
1!
#1330
0!
#1340
b110111110000 )
b110111110000 0
b1000001111 *
b1000001111 7
b101001 @
b10000000 1
b100000000 C
1!
#1350
0!
#1360
b111000000000 )
b111000000000 0
b111111111 *
b111111111 7
b11001 @
b1000000 1
b10000000 C
1!
#1370
0!
#1380
b111000001010 )
b111000001010 0
b111110101 *
b111110101 7
b1111 @
b100000 1
b1000000 C
1!
#1390
0!
#1400
b111000010000 )
b111000010000 0
b111101111 *
b111101111 7
b1001 @
b10000 1
b100000 C
1!
#1410
0!
#1420
b111000010011 )
b111000010011 0
b111101100 *
b111101100 7
b110 @
b10 6
1.
1/
b10000 1
b10000 C
1!
#1430
0!
#1440
b11 6
b10 =
1!
#1450
b1 5
0!
1#
#1460
b10 5
b100 6
b1 >
b11 =
1!
#1470
b1 5
0!
0#
#1480
b101 6
b100 =
1!
#1490
b10 5
0!
1#
#1500
b11 5
b110 6
b10 >
b101 =
1!
#1510
b10 5
0!
0#
#1520
b111 6
b110 =
1!
#1530
0!
#1540
b1000 1
b0 5
0.
b1 6
b111 =
1!
#1550
0!
#1560
b111000010101 )
b111000010101 0
b111101010 *
b111101010 7
b100 @
b1000 1
b10 6
1/
1.
b0 >
b1 =
b1000 C
1!
#1570
0!
#1580
b11 6
b10 =
1!
#1590
0!
#1600
b100 6
b11 =
1!
#1610
0!
#1620
b101 6
b100 =
1!
#1630
0!
#1640
b110 6
b101 =
1!
#1650
0!
#1660
b111 6
b110 =
1!
#1670
0!
#1680
b100 1
0.
b1 6
b111 =
1!
#1690
b1 5
0!
1#
#1700
b111000010111 )
b111000010111 0
b111101000 *
b111101000 7
b10 @
b111100110 4
b100 1
09
1/
b10 6
b10 5
1.
b1 >
b1 =
b100 C
1!
#1710
0!
#1720
b11 5
b11 6
b10 >
b10 =
1!
#1730
b10 5
0!
0#
